autora/theorist/darts/__init__.py
autora/theorist/darts/architect.py
autora/theorist/darts/dataset.py
autora/theorist/darts/fan_out.py
autora/theorist/darts/model_search.py
autora/theorist/darts/operations.py
autora/theorist/darts/regressor.py
autora/theorist/darts/utils.py
autora/theorist/darts/visualize.py
autora_theorist_darts-1.1.0.dist-info/LICENSE
autora_theorist_darts-1.1.0.dist-info/METADATA
autora_theorist_darts-1.1.0.dist-info/WHEEL
autora_theorist_darts-1.1.0.dist-info/top_level.txt
autora_theorist_darts-1.1.0.dist-info/RECORD
