Metadata-Version: 2.1
Name: autora-theorist-darts
Version: 1.1.0
Summary: Differentiable Architecture Search theorist for AutoRA
Author-email: Sebastian Musslick <sebastian_musslick@brown.edu>, John Gerrard Holland <john_holland1@brown.edu>
License: MIT License
Project-URL: homepage, http://www.empiricalresearch.ai
Project-URL: repository, https://github.com/AutoResearch/autora-theorist-darts
Project-URL: documentation, https://autoresearch.github.io/autora/
License-File: LICENSE
Requires-Dist: autora-core
Requires-Dist: scikit-learn
Requires-Dist: torch
Requires-Dist: matplotlib
Requires-Dist: graphviz
Requires-Dist: tqdm
Provides-Extra: dev
Requires-Dist: autora-core[dev] ; extra == 'dev'
Requires-Dist: autora-synthetic ; extra == 'dev'
